rescal/__init__.py
rescal/rescal.py
rescal/version.py
rescal-0.4.dist-info/LICENSE
rescal-0.4.dist-info/METADATA
rescal-0.4.dist-info/WHEEL
rescal-0.4.dist-info/top_level.txt
rescal-0.4.dist-info/RECORD
