Metadata-Version: 2.1
Name: rescal
Version: 0.4
Summary: Python module to compute the RESCAL tensor factorization
Home-page: http://github.com/mnick/rescal.py
Author: Maximilian Nickel
Author-email: mnick@mit.edu
Maintainer: Remi Rampin
Maintainer-email: remi@rampin.org
License: GPLv3
Download-URL: http://github.com/mnick/rescal.py
Platform: UNKNOWN
Classifier: Development Status :: 4 - Beta
Classifier: Intended Audience :: Developers
Classifier: Intended Audience :: Science/Research
Classifier: License :: OSI Approved :: GNU General Public License v3 (GPLv3)
Classifier: Topic :: Scientific/Engineering
Classifier: Topic :: Software Development
Classifier: Operating System :: Microsoft :: Windows
Classifier: Operating System :: POSIX
Classifier: Operating System :: Unix
Classifier: Operating System :: MacOS
Classifier: Programming Language :: Python :: 2
Classifier: Programming Language :: Python :: 2.6
Classifier: Programming Language :: Python :: 2.7
Classifier: Programming Language :: Python :: 3
Classifier: Programming Language :: Python :: 3.3
License-File: LICENSE
